pantomime/__init__.py
pantomime/filename.py
pantomime/mappings.py
pantomime/mime.py
pantomime/parse.py
pantomime/py.typed
pantomime/types.py
pantomime/util.py
tests/__init__.py
tests/test_extension.py
tests/test_filename.py
tests/test_mime.py
pantomime-0.6.1.dist-info/LICENSE
pantomime-0.6.1.dist-info/METADATA
pantomime-0.6.1.dist-info/WHEEL
pantomime-0.6.1.dist-info/namespace_packages.txt
pantomime-0.6.1.dist-info/top_level.txt
pantomime-0.6.1.dist-info/RECORD
