Metadata-Version: 2.1
Name: pantomime
Version: 0.6.1
Summary: MIME type normalisation and labels.
Home-page: http://github.com/alephdata/pantomime
Author: Journalism Development Network, Inc.
Author-email: data@occrp.org
License: MIT
Keywords: mime mimetypes file types
Classifier: Development Status :: 3 - Alpha
Classifier: Intended Audience :: Developers
Classifier: License :: OSI Approved :: MIT License
Classifier: Operating System :: OS Independent
Classifier: Programming Language :: Python :: 2.7
Classifier: Programming Language :: Python :: 3.3
Classifier: Programming Language :: Python :: 3.6
License-File: LICENSE
Requires-Dist: banal (>=0.3.5)
Requires-Dist: normality (>=0.5.6)
Provides-Extra: dev
Requires-Dist: wheel (>=0.29.0) ; extra == 'dev'
Requires-Dist: twine ; extra == 'dev'
Requires-Dist: mypy ; extra == 'dev'
Requires-Dist: black ; extra == 'dev'
Requires-Dist: flake8 (>=2.6.0) ; extra == 'dev'
Requires-Dist: pytest ; extra == 'dev'
Requires-Dist: pytest-cov ; extra == 'dev'
Requires-Dist: banal ; extra == 'dev'
Requires-Dist: coverage (>=4.1) ; extra == 'dev'
